odoo/addons/donation/README.rst
odoo/addons/donation/__init__.py
odoo/addons/donation/__manifest__.py
odoo/addons/donation/post_install.py
odoo/addons/donation/data/donation_sequence.xml
odoo/addons/donation/demo/donation_demo.xml
odoo/addons/donation/i18n/de.po
odoo/addons/donation/i18n/donation.pot
odoo/addons/donation/i18n/es.po
odoo/addons/donation/i18n/fr.po
odoo/addons/donation/i18n/it.po
odoo/addons/donation/migrations/14.0.1.0.0/post-migration.py
odoo/addons/donation/migrations/14.0.1.0.0/pre-migration.py
odoo/addons/donation/models/__init__.py
odoo/addons/donation/models/account_bank_statement.py
odoo/addons/donation/models/account_journal.py
odoo/addons/donation/models/account_payment_mode.py
odoo/addons/donation/models/donation.py
odoo/addons/donation/models/donation_campaign.py
odoo/addons/donation/models/donation_tax_receipt.py
odoo/addons/donation/models/donation_thanks_template.py
odoo/addons/donation/models/res_company.py
odoo/addons/donation/models/res_partner.py
odoo/addons/donation/models/res_users.py
odoo/addons/donation/readme/CONFIGURE.rst
odoo/addons/donation/readme/CONTRIBUTORS.rst
odoo/addons/donation/readme/DESCRIPTION.rst
odoo/addons/donation/readme/USAGE.rst
odoo/addons/donation/report/__init__.py
odoo/addons/donation/report/donation_report.py
odoo/addons/donation/report/donation_report_view.xml
odoo/addons/donation/report/donation_thanks_report.xml
odoo/addons/donation/report/donation_thanks_view.xml
odoo/addons/donation/security/donation_security.xml
odoo/addons/donation/security/ir.model.access.csv
odoo/addons/donation/static/description/icon.png
odoo/addons/donation/static/description/icon.svg
odoo/addons/donation/static/description/index.html
odoo/addons/donation/tests/__init__.py
odoo/addons/donation/tests/test_donation.py
odoo/addons/donation/views/account_bank_statement.xml
odoo/addons/donation/views/account_journal.xml
odoo/addons/donation/views/account_payment_mode.xml
odoo/addons/donation/views/donation.xml
odoo14_addon_donation-14.0.1.8.0.dist-info/METADATA
odoo14_addon_donation-14.0.1.8.0.dist-info/WHEEL
odoo14_addon_donation-14.0.1.8.0.dist-info/top_level.txt
odoo14_addon_donation-14.0.1.8.0.dist-info/RECORD
